mantas_j_mod1_atsiskaitymas/__init__.py
mantas_j_mod1_atsiskaitymas/crawler.py
mantas_j_mod1_atsiskaitymas/data_parser.py
mantas_j_mod1_atsiskaitymas/main.py
mantas_j_mod1_atsiskaitymas/web_crawler.py
tests/__init__.py
tests/test_crawler.py
tests/test_data_parser.py
mantas_j_mod1_atsiskaitymas-0.4.0.dist-info/METADATA
mantas_j_mod1_atsiskaitymas-0.4.0.dist-info/WHEEL
mantas_j_mod1_atsiskaitymas-0.4.0.dist-info/top_level.txt
mantas_j_mod1_atsiskaitymas-0.4.0.dist-info/RECORD
